examples/__init__.py
examples/basic_usage.py
examples/custom_logger.py
logease/__init__.py
logease/__pycache__/__init__.cpython-311.pyc
logease/config/__init__.py
logease/config/settings.py
logease/config/__pycache__/__init__.cpython-311.pyc
logease/config/__pycache__/settings.cpython-311.pyc
logease/decorators/__init__.py
logease/decorators/detail.py
logease/decorators/tracer.py
logease/decorators/__pycache__/__init__.cpython-311.pyc
logease/decorators/__pycache__/tracer.cpython-311.pyc
logease/handlers/__init__.py
logease/handlers/request.py
logease/handlers/__pycache__/__init__.cpython-311.pyc
logease/handlers/__pycache__/request.cpython-311.pyc
logease/modules/__init__.py
logease/modules/logger.py
logease/modules/__pycache__/__init__.cpython-311.pyc
logease/modules/__pycache__/logger.cpython-311.pyc
logease/utils/__init__.py
tests/__init__.py
tests/test_config.py
tests/test_decorators.py
tests/test_logger.py
logease-0.2.0.dist-info/LICENSE
logease-0.2.0.dist-info/METADATA
logease-0.2.0.dist-info/WHEEL
logease-0.2.0.dist-info/top_level.txt
logease-0.2.0.dist-info/RECORD
