Metadata-Version: 2.1
Name: logease
Version: 0.2.0
Summary: A Python logging library designed to replace traditional logging mechanisms using decorators and modules.
Home-page: https://github.com/Latrodect/Logease
Author: Bahadir Nural
Author-email: bahadir.nural@outlook.com
Classifier: Programming Language :: Python :: 3
Classifier: License :: OSI Approved :: MIT License
Classifier: Operating System :: OS Independent
License-File: LICENSE
Requires-Dist: colorlog
Requires-Dist: pysnmp
